bl_event_sourcing_sqlalchemy/__init__.py
bl_event_sourcing_sqlalchemy/core.py
bl_event_sourcing_sqlalchemy/py.typed
bl_event_sourcing_sqlalchemy-0.2.1.dist-info/LICENSE.md
bl_event_sourcing_sqlalchemy-0.2.1.dist-info/WHEEL
bl_event_sourcing_sqlalchemy-0.2.1.dist-info/METADATA
bl_event_sourcing_sqlalchemy-0.2.1.dist-info/RECORD
